{
  "name": "RESTful Students",
  "dockerComposeFile": "docker-compose.yml",
  "service": "app",
  "runServices": [
    "app",
    "db-postgres",
    "db-mysql",
    "cache-redis"
  ],
  "workspaceFolder": "/workspace",
  "settings": {},
  "extensions": [
    "dbaeumer.vscode-eslint",
    "esbenp.prettier-vscode",
    "ms-vscode.vscode-typescript-next",
    "streetsidesoftware.code-spell-checker",
    "streetsidesoftware.code-spell-checker-portuguese-brazilian"
  ],
  "remoteUser": "node",
  "shutdownAction": "stopCompose"
}